MANIFEST.in
README.rst
setup.cfg
setup.py
pysend/__init__.py
pysend/classes.py
pysend/sendgridWebApi.py
pysend/smtp.py
pysend.egg-info/PKG-INFO
pysend.egg-info/SOURCES.txt
pysend.egg-info/dependency_links.txt
pysend.egg-info/requires.txt
pysend.egg-info/top_level.txt